sns_appointment_pkg/__init__.py
sns_appointment_pkg/notification/__init__.py
sns_appointment_pkg/notification/appointment.py
sns_appointment_pkg/notification/client.py
sns_appointment-0.2.0.dist-info/LICENSE
sns_appointment-0.2.0.dist-info/METADATA
sns_appointment-0.2.0.dist-info/WHEEL
sns_appointment-0.2.0.dist-info/top_level.txt
sns_appointment-0.2.0.dist-info/RECORD
