Metadata-Version: 2.2
Name: sns-appointment
Version: 0.2.0
Summary: A library for sending AWS SNS notifications for doctor appointments
Home-page: https://github.com/Jeena7758
Author: Jeena
Author-email: jeena7758@gmail.com
Classifier: Programming Language :: Python :: 3
Classifier: License :: OSI Approved :: MIT License
Classifier: Operating System :: OS Independent
Requires-Python: >=3.6
License-File: LICENSE
Requires-Dist: boto3>=1.17.0
Dynamic: author
Dynamic: author-email
Dynamic: classifier
Dynamic: description-content-type
Dynamic: home-page
Dynamic: requires-dist
Dynamic: requires-python
Dynamic: summary
